[
  {
    "text": "Invoice No. 1213\n16.12.2021\nTo\nLa Galerie\n4 Rue Courtois\nLille, Nord, 59000\nShip To\nSame as recipient\nInstructions\nNone\nProduct Unit Price [EUR] Total [EUR]\nGlossostigma\nQty. 3 9.90 29.70\nBayberry\nQty. 222 5.44 1,207.68\nWaxflower\nQty. 34 1.67 56.78\nCarolina Geranium\nQty. 45 4.17 187.65\nSmooth Solomon's\nSeal\nQty. 3 4.97 14.91\nEl Yunque Colorado\nQty. 23 9.97 229.31\nZencorporations\nTel + 49 228 698629 Thomas-Mann-Strasse 38 zencorporations.de\nFax + 49 228 698629 Bonn, 53111 contact@zencorporations.de",
    "page": 1,
    "paragraph": 1
  },
  {
    "text": "Invoice No. 1213\n16.12.2021\nQueen Anne's Lace\nQty. 32 6.05 193.60\nAlaskan Douglasia\nQty. 122 4.36 531.92\nDeer Sedge\nQty. 23 3.82 87.86\nIndian Tobacco\nQty. 2 7.25 14.50\nSubtotal 2553.91\nSales Tax 255.39\nTotal Due 2809.30\nDue 30 days after receipt\nThank you for your business!\n2",
    "page": 2,
    "paragraph": 1
  }
]